pyblaze/__init__.py
pyblaze/multiprocessing/__init__.py
pyblaze/multiprocessing/vectorize.py
pyblaze/nn/__init__.py
pyblaze/nn/callbacks/__init__.py
pyblaze/nn/callbacks/base.py
pyblaze/nn/callbacks/early_stopping.py
pyblaze/nn/callbacks/logging.py
pyblaze/nn/callbacks/saving.py
pyblaze/nn/callbacks/schedule.py
pyblaze/nn/callbacks/tracking.py
pyblaze/nn/data/__init__.py
pyblaze/nn/data/extensions.py
pyblaze/nn/data/noise.py
pyblaze/nn/data/transform.py
pyblaze/nn/data/zip.py
pyblaze/nn/engine/__init__.py
pyblaze/nn/engine/_history.py
pyblaze/nn/engine/_utils.py
pyblaze/nn/engine/autoencoder.py
pyblaze/nn/engine/base.py
pyblaze/nn/engine/mle.py
pyblaze/nn/engine/wgan.py
pyblaze/nn/functional/__init__.py
pyblaze/nn/functional/densities.py
pyblaze/nn/functional/metrics.py
pyblaze/nn/functional/softgrad.py
pyblaze/nn/modules/__init__.py
pyblaze/nn/modules/distribution.py
pyblaze/nn/modules/gp.py
pyblaze/nn/modules/lstm.py
pyblaze/nn/modules/made.py
pyblaze/nn/modules/normalizing.py
pyblaze/nn/modules/residual.py
pyblaze/nn/modules/transforms.py
pyblaze/nn/modules/vae.py
pyblaze/nn/modules/view.py
pyblaze/nn/modules/wasserstein.py
pyblaze/nn/utils/__init__.py
pyblaze/nn/utils/data_parallel.py
pyblaze/nn/utils/estimator.py
pyblaze/optim/__init__.py
pyblaze/optim/lamb.py
pyblaze/plot/__init__.py
pyblaze/plot/density.py
pyblaze/utils/__init__.py
pyblaze/utils/stdio.py
pyblaze/utils/stdlib.py
pyblaze/utils/stdmp.py
pyblaze/utils/torch.py
pyblaze/utils/examples/__init__.py
pyblaze/utils/examples/normalizing_flows.py
tests/__init__.py
tests/multiprocessing/__init__.py
tests/multiprocessing/test_vectorizer.py
tests/nn/__init__.py
tests/nn/functional/__init__.py
tests/nn/functional/test_metrics.py
tests/nn/modules/__init__.py
tests/nn/modules/test_lstm.py
tests/nn/modules/test_made.py
pyblaze-2.3.2.dist-info/LICENSE
pyblaze-2.3.2.dist-info/METADATA
pyblaze-2.3.2.dist-info/WHEEL
pyblaze-2.3.2.dist-info/top_level.txt
pyblaze-2.3.2.dist-info/RECORD
