Metadata-Version: 2.1
Name: pyblaze
Version: 2.3.2
Summary: Large-Scale Machine and Deep Learning in PyTorch.
Home-page: https://github.com/borchero/pyblaze
Author: Oliver Borchert
Author-email: borchero@icloud.com
License: License :: OSI Approved :: MIT License
Platform: UNKNOWN
Classifier: Development Status :: 5 - Production/Stable
Classifier: Programming Language :: Python :: 3.7
Classifier: Topic :: Software Development :: Libraries
Requires-Python: >=3.7
Requires-Dist: torch (<2.0.0,>=1.4.0)
Requires-Dist: numpy (<2.0.0,>=1.18.2)
Requires-Dist: scipy (<2.0.0,>=1.4.1)
Requires-Dist: numba (<1.0.0,>=0.48.0)
Requires-Dist: scikit-learn (<0.25.0,>=0.23.0)
Requires-Dist: tensorboard (<3.0.0,>=2.2.0)
Requires-Dist: matplotlib (<4.0.0,>=3.0.0)
